MLAMA/GridSearch.py
MLAMA/Models.py
MLAMA/Predictions.py
MLAMA/Processor.py
MLAMA/Visualization.py
MLAMA/Wave.py
MLAMA/Weighted.py
MLAMA/__init__.py
MLAMA/main.py
mlama-0.1.126.dist-info/METADATA
mlama-0.1.126.dist-info/WHEEL
mlama-0.1.126.dist-info/top_level.txt
mlama-0.1.126.dist-info/RECORD
