Metadata-Version: 2.2
Name: MLAMA
Version: 0.1.126
Summary: MLAMA test package by Johra Moosa
Home-page: https://github.com/yourusername/testbyjohra
Author: Johra Moosa
Author-email: your_email@example.com
Requires-Python: >=3.6
Dynamic: author
Dynamic: author-email
Dynamic: description
Dynamic: description-content-type
Dynamic: home-page
Dynamic: requires-python
Dynamic: summary
